klipper_jsonrpc/__init__.py
klipper_jsonrpc/klipper_client.py
klipper_jsonrpc-0.2.0.dist-info/METADATA
klipper_jsonrpc-0.2.0.dist-info/WHEEL
klipper_jsonrpc-0.2.0.dist-info/entry_points.txt
klipper_jsonrpc-0.2.0.dist-info/licenses/LICENSE
klipper_jsonrpc-0.2.0.dist-info/RECORD
