Metadata-Version: 2.4
Name: klipper-jsonrpc
Version: 0.2.0
Summary: Add your description here
Author-email: Rui Kobayashi <roboroborx782@gmail.com>
License: MIT License
License-File: LICENSE
Requires-Python: >=3.10
Requires-Dist: aiohttp>=3.11.16
